{
  "$schema": "https://schemas.wp.org/trunk/theme.json",
  "title": "Purple",
  "version": 2,
  "settings": {
    "color": {
      "palette": [
        { 
          "name": "Primary", 
          "color": "#6D28D9", 
          "slug": "primary" 
        },
        { 
          "name": "Secondary", 
          "color": "#D97706", 
          "slug": "secondary" 
        },
        { 
          "name": "Tertiary", 
          "color": "#1E1B4B", 
          "slug": "tertiary" 
        },
        { 
          "name": "Quaternary", 
          "color": "#FACC15", 
          "slug": "quaternary" 
        },
        {
          "name": "Accent",
          "color": "#5733FE",
          "slug": "accent"
        },
        {
          "name": "Accent Text",
          "color": "#FFFFFE",
          "slug": "accent-text"
        },
        {
          "name": "Heading",
          "color": "#162136",
          "slug": "heading"
        },
        {
          "name": "Highlight",
          "color": "#4B5563",
          "slug": "highlight"
        },
        {
          "name": "Body",
          "color": "#0A0B0F99",
          "slug": "body"
        },
        {
          "name": "Background",
          "color": "#FFFFFD",
          "slug": "background"
        },
        {
          "name": "Light",
          "color": "#EBEEFC",
          "slug": "light"
        },
        {
          "name": "Outline",
          "color": "#E5E7EB",
          "slug": "outline"
        },
        {
          "name": "Neutral",
          "color": "#9CA3AF",
          "slug": "neutral"
        },
        {
          "name": "Foreground",
          "color": "#111827",
          "slug": "foreground"
        },
        {
          "name": "Transparent",
          "color": "transparent",
          "slug": "transparent"
        },
        {
          "name": "Current Color",
          "color": "currentColor",
          "slug": "currentColor"
        },
        {
          "name": "Inherit",
          "color": "inherit",
          "slug": "inherit"
        },
        {
          "name": "Pure White",
          "color": "#FFFFFF",
          "slug": "pure-white"
        },
        {
          "name": "Pure Black",
          "color": "#000000",
          "slug": "pure-black"
        }
],
      "gradients": [
        {
          "name": "Primary",
          "slug": "primary",
          "gradient": "linear-gradient(285deg, #ac6bff -1.5%, #0C1B5D 100%)"
        }
      ],
      "duotone": [
        {
          "name": "Primary",
          "slug": "primary",
          "colors": [
            "#ac6bff",
            "#ac6bff"
          ]
        },
        {
          "name": "Secondary",
          "slug": "secondary",
          "colors": [
            "#0C1B5D",
            "#0C1B5D"
          ]
        },
        {
          "name": "Light",
          "slug": "light",
          "colors": [
            "#ffffff",
            "#ffffff"
          ]
        }
      ]
    }
  }
}
